hf_inference_acp/__init__.py
hf_inference_acp/agents.py
hf_inference_acp/cli.py
hf_inference_acp/hf_config.py
hf_inference_acp/resources/hf.config.yaml
hf_inference_acp/resources/hf.system_prompt.md
hf_inference_acp/wizard/__init__.py
hf_inference_acp/wizard/model_catalog.py
hf_inference_acp/wizard/stages.py
hf_inference_acp/wizard/wizard_llm.py
hf_inference_acp-0.4.46.dist-info/METADATA
hf_inference_acp-0.4.46.dist-info/WHEEL
hf_inference_acp-0.4.46.dist-info/entry_points.txt
hf_inference_acp-0.4.46.dist-info/licenses/LICENSE
hf_inference_acp-0.4.46.dist-info/RECORD
