Metadata-Version: 2.4
Name: hf-inference-acp
Version: 0.4.46
Summary: Hugging Face inference agent with ACP support, powered by fast-agent-mcp
Project-URL: Homepage, https://github.com/evalstate/fast-agent
Project-URL: Repository, https://github.com/evalstate/fast-agent
Project-URL: Issues, https://github.com/evalstate/fast-agent/issues
Author-email: Fast Agent Maintainers <fastagent@llmindset.co.uk>
License: Apache-2.0
License-File: LICENSE
Classifier: License :: OSI Approved :: Apache Software License
Classifier: Operating System :: OS Independent
Classifier: Programming Language :: Python :: 3
Requires-Python: <3.14,>=3.13.5
Requires-Dist: fast-agent-mcp==0.4.46
Requires-Dist: huggingface-hub>=1.3.4
